iterio_commons/__init__.py
iterio_commons/logging_setup.py
iterio_commons-0.2.0.dist-info/METADATA
iterio_commons-0.2.0.dist-info/RECORD
iterio_commons-0.2.0.dist-info/WHEEL
iterio_commons-0.2.0.dist-info/top_level.txt
