Metadata-Version: 2.1
Name: iterio-commons
Version: 0.2.0
Summary: Common code of Iterio's Python codebases.
Home-page: https://github.com/iteriodata/iterio-commons
Author: UNKNOWN
Author-email: UNKNOWN
License: MIT
Project-URL: Bug Reports, https://github.com/iteriodata/iterio-commons/issues
Project-URL: Source, https://github.com/iteriodata/iterio-commons
Keywords: iterio
Platform: UNKNOWN
Classifier: Programming Language :: Python :: 3.6
Classifier: Operating System :: POSIX :: Linux
Classifier: License :: OSI Approved :: MIT License
Classifier: Development Status :: 4 - Beta
Classifier: Intended Audience :: Developers
Classifier: Natural Language :: English
Requires-Dist: structlog
